wave_train/__init__.py
wave_train/dynamics/__init__.py
wave_train/dynamics/ceom.py
wave_train/dynamics/class_mech.py
wave_train/dynamics/mechanics.py
wave_train/dynamics/qcmd.py
wave_train/dynamics/qu_cl_mech.py
wave_train/dynamics/quant_mech.py
wave_train/dynamics/tdse.py
wave_train/dynamics/tise.py
wave_train/graphics/__init__.py
wave_train/graphics/animation.py
wave_train/graphics/exceptions.py
wave_train/graphics/factory.py
wave_train/graphics/helper.py
wave_train/graphics/services.py
wave_train/graphics/style.py
wave_train/graphics/visual.py
wave_train/hamilton/__init__.py
wave_train/hamilton/bath_map_1.py
wave_train/hamilton/chain.py
wave_train/hamilton/exc_pho_coupling.py
wave_train/hamilton/exciton.py
wave_train/hamilton/phonon.py
wave_train/io/__init__.py
wave_train/io/collect3.py
wave_train/io/collect4_a.py
wave_train/io/collect4_b.py
wave_train/io/load.py
wave_train/io/logging.py
wave_train-1.0.11.dist-info/LICENSE
wave_train-1.0.11.dist-info/METADATA
wave_train-1.0.11.dist-info/WHEEL
wave_train-1.0.11.dist-info/top_level.txt
wave_train-1.0.11.dist-info/RECORD
