Metadata-Version: 2.1
Name: wave-train
Version: 1.0.11
Summary: Numerical quantum mechanics of chain-like systems based on tensor trains
Author: Jerome Riedel, Patrick Gelß, Burkhard Schmidt
Author-email: burkhard.schmidt@fu-berlin.de
License: GNU v3.0
Requires-Python: <4,>=3.7
License-File: LICENSE
Requires-Dist: matplotlib >=3.4.3
Requires-Dist: numpy >=1.21.2
Requires-Dist: scipy >=1.7.1
Requires-Dist: sympy >=1.9
